{
  "generated_at": "2026-03-21T02:10:01.248Z",
  "status": "pass",
  "passed": 5,
  "failed": 0,
  "checks": [
    {
      "id": "parity_all_waves_closeout_artifacts_present",
      "pass": true,
      "detail": "wave1:present, wave2:present, wave3:present, wave4:present, wave5:present, wave6:present, wave7:present, wave8:present"
    },
    {
      "id": "parity_all_waves_closeout_status_pass",
      "pass": true,
      "detail": "wave1:pass, wave2:pass, wave3:pass, wave4:pass, wave5:pass, wave6:pass, wave7:pass, wave8:pass"
    },
    {
      "id": "parity_all_waves_ci_binding_present",
      "pass": true,
      "detail": "parity-e2e workflow executes and uploads the unified all-waves closeout artifact"
    },
    {
      "id": "parity_all_waves_npm_aliases_present",
      "pass": true,
      "detail": "package.json exposes all-waves closeout aliases"
    },
    {
      "id": "parity_all_waves_program_snapshot_present",
      "pass": true,
      "detail": "competitive reproduction program includes all-waves closeout snapshot pointer"
    }
  ]
}
